utils/__init__.py
utils/get_website_encoding.py
example_package_smawe-0.0.5.dist-info/LICENSE
example_package_smawe-0.0.5.dist-info/METADATA
example_package_smawe-0.0.5.dist-info/WHEEL
example_package_smawe-0.0.5.dist-info/top_level.txt
example_package_smawe-0.0.5.dist-info/RECORD
